rofi.py
python_rofi_phfn-1.0.3.dist-info/LICENSE
python_rofi_phfn-1.0.3.dist-info/WHEEL
python_rofi_phfn-1.0.3.dist-info/METADATA
python_rofi_phfn-1.0.3.dist-info/RECORD
