Metadata-Version: 2.1
Name: python-rofi-phfn
Version: 1.0.3
Summary: Create simple GUIs using the Rofi application
Author-email: Paul Hoffmann <phfn@phfn.de>, Blair Bonnett <blair.bonnett@gmail.com>, Marco Köpcke <marco.koepke@tudock.de>
Classifier: License :: OSI Approved :: MIT License
Project-URL: Source, https://github.com/phfn/python-rofi
